velib_spot_predictor/__init__.py
velib_spot_predictor/api/__init__.py
velib_spot_predictor/api/database/__init__.py
velib_spot_predictor/api/database/models.py
velib_spot_predictor/api/database/routes.py
velib_spot_predictor/api/prediction/__init__.py
velib_spot_predictor/api/prediction/models.py
velib_spot_predictor/api/prediction/routes.py
velib_spot_predictor/data/__init__.py
velib_spot_predictor/data/base.py
velib_spot_predictor/data/cli.py
velib_spot_predictor/data/constants.py
velib_spot_predictor/data/database/__init__.py
velib_spot_predictor/data/database/alembic/README
velib_spot_predictor/data/database/alembic/env.py
velib_spot_predictor/data/database/alembic/script.py.mako
velib_spot_predictor/data/database/alembic/versions/9e32ab3f9fca_create_station_tables.py
velib_spot_predictor/data/database/context.py
velib_spot_predictor/data/database/models.py
velib_spot_predictor/data/fetch.py
velib_spot_predictor/data/geo.py
velib_spot_predictor/data/load_data.py
velib_spot_predictor/data/publish.py
velib_spot_predictor/environment.py
velib_spot_predictor/front/__init__.py
velib_spot_predictor/front/app.py
velib_spot_predictor/model/__init__.py
velib_spot_predictor/model/predict_model.py
velib_spot_predictor/model/save_model.py
velib_spot_predictor/model/train_model.py
velib_spot_predictor/utils.py
velib_spot_predictor-0.4.0.dist-info/METADATA
velib_spot_predictor-0.4.0.dist-info/WHEEL
velib_spot_predictor-0.4.0.dist-info/entry_points.txt
velib_spot_predictor-0.4.0.dist-info/RECORD
